Metadata-Version: 1.0
Name: razzpy
Version: 0.2
Summary: Gaussian distributions
Home-page: UNKNOWN
Author: Ridho Gani
Author-email: ridhoadhadigani@gmail.com
License: UNKNOWN
Platform: UNKNOWN
